{
  "reportFormat": "CTRF",
  "specVersion": "0.0.0",
  "results": {
    "tool": {
      "name": "JUnit"
    },
    "summary": {
      "tests": 7,
      "passed": 7,
      "failed": 0,
      "pending": 0,
      "skipped": 0,
      "other": 0,
      "start": 1766484000000,
      "stop": 1766484015000
    },
    "tests": [
      {
        "name": "Verify data export to CSV format",
        "status": "passed",
        "duration": 1523,
        "start": 1766484001000,
        "stop": 1766484002523,
        "tags": ["success", "long", "fake"],
        "filepath": "io.github.alexshamrai.FirstLongTest",
        "threadId": "Test worker"
      },
      {
        "name": "Verify email notification delivery",
        "status": "passed",
        "duration": 1112,
        "start": 1766484003000,
        "stop": 1766484004112,
        "tags": ["success", "long", "fake"],
        "filepath": "io.github.alexshamrai.FirstLongTest",
        "threadId": "Test worker"
      },
      {
        "name": "Verify batch processing completion",
        "status": "passed",
        "duration": 2534,
        "start": 1766484004500,
        "stop": 1766484007034,
        "tags": ["success", "long", "fake"],
        "filepath": "io.github.alexshamrai.FirstLongTest",
        "threadId": "Test worker"
      },
      {
        "name": "Verify report generation with large dataset",
        "status": "passed",
        "duration": 1589,
        "start": 1766484007500,
        "stop": 1766484009089,
        "tags": ["success", "long", "fake"],
        "filepath": "io.github.alexshamrai.SecondLongTest",
        "threadId": "Test worker"
      },
      {
        "name": "Verify cache invalidation across nodes",
        "status": "passed",
        "duration": 1134,
        "start": 1766484009500,
        "stop": 1766484010634,
        "tags": ["success", "long", "fake"],
        "filepath": "io.github.alexshamrai.SecondLongTest",
        "threadId": "Test worker"
      },
      {
        "name": "Verify full database migration",
        "status": "passed",
        "duration": 2656,
        "start": 1766484011000,
        "stop": 1766484013656,
        "tags": ["success", "long", "fake"],
        "filepath": "io.github.alexshamrai.SecondLongTest",
        "threadId": "Test worker"
      },
      {
        "name": "Verify external service response timeout",
        "status": "passed",
        "duration": 1087,
        "start": 1766484014000,
        "stop": 1766484015087,
        "tags": ["flaky", "fake"],
        "filepath": "io.github.alexshamrai.FlakyTest",
        "threadId": "Test worker"
      }
    ],
    "environment": {
      "buildName": "Regression",
      "buildNumber": "201",
      "buildUrl": "https://github.com/alexshamrai/dummy-tests-junit/actions/runs/12345201",
      "commit": "a1b2c3d4e5f6789012345678901234567890abcd",
      "branchName": "master"
    }
  }
}
